karton_classifier-2.1.0-nspkg.pth
karton/classifier/__init__.py
karton/classifier/__main__.py
karton/classifier/__version__.py
karton/classifier/classifier.py
karton_classifier-2.1.0.dist-info/LICENSE
karton_classifier-2.1.0.dist-info/METADATA
karton_classifier-2.1.0.dist-info/WHEEL
karton_classifier-2.1.0.dist-info/entry_points.txt
karton_classifier-2.1.0.dist-info/namespace_packages.txt
karton_classifier-2.1.0.dist-info/top_level.txt
karton_classifier-2.1.0.dist-info/RECORD
