Metadata-Version: 2.1
Name: karton-classifier
Version: 2.1.0
Summary: File type classifier for Karton framework
Home-page: https://github.com/CERT-Polska/karton-classifier/
Classifier: Programming Language :: Python
Classifier: Operating System :: OS Independent
License-File: LICENSE
Requires-Dist: chardet ==3.0.4
Requires-Dist: karton-core <6.0.0,>=5.0.0
Requires-Dist: python-magic ==0.4.18
Requires-Dist: yara-python <5.0.0,>=4.0.0
